discrete_structures_mcp/__init__.py
discrete_structures_mcp/server.py
discrete_structures_mcp/tools/__init__.py
discrete_structures_mcp/tools/algorithms.py
discrete_structures_mcp/tools/cryptography.py
discrete_structures_mcp/tools/logic.py
discrete_structures_mcp/tools/number_theory.py
discrete_structures_mcp-0.1.4.dist-info/METADATA
discrete_structures_mcp-0.1.4.dist-info/WHEEL
discrete_structures_mcp-0.1.4.dist-info/entry_points.txt
discrete_structures_mcp-0.1.4.dist-info/licenses/LICENSE
discrete_structures_mcp-0.1.4.dist-info/RECORD
