Metadata-Version: 2.4
Name: discrete-structures-mcp
Version: 0.1.4
Summary: MCP server for Discrete Mathematics: Boolean Logic, Algorithms, Number Theory, Cryptography. 21 AI-ready tools for education and research.
Project-URL: Homepage, https://github.com/ZohaibCodez/discrete-structures-ai-platform
Project-URL: Repository, https://github.com/ZohaibCodez/discrete-structures-ai-platform
Project-URL: Issues, https://github.com/ZohaibCodez/discrete-structures-ai-platform/issues
Project-URL: Documentation, https://github.com/ZohaibCodez/discrete-structures-ai-platform#readme
Author-email: ZohaibCodez <zohaib@example.com>
License: MIT
License-File: LICENSE
Keywords: aes,ai-tools,algorithms,boolean-logic,claude,computer-science,cryptography,discrete-mathematics,discrete-structures,education,graph-algorithms,llm,mathematics,mcp,model-context-protocol,modular-arithmetic,number-theory,prime-numbers,rsa,sorting-algorithms,truth-tables
Classifier: Development Status :: 4 - Beta
Classifier: Framework :: AsyncIO
Classifier: Intended Audience :: Developers
Classifier: Intended Audience :: Education
Classifier: Intended Audience :: Science/Research
Classifier: License :: OSI Approved :: MIT License
Classifier: Operating System :: OS Independent
Classifier: Programming Language :: Python :: 3.11
Classifier: Programming Language :: Python :: 3.12
Classifier: Programming Language :: Python :: 3.13
Classifier: Topic :: Education
Classifier: Topic :: Scientific/Engineering :: Mathematics
Classifier: Topic :: Security :: Cryptography
Classifier: Topic :: Software Development :: Libraries :: Python Modules
Requires-Python: >=3.11
Requires-Dist: cryptography>=42.0.0
Requires-Dist: mcp>=1.0.0
Requires-Dist: networkx>=3.0
Requires-Dist: numpy>=1.26.0
Requires-Dist: sympy>=1.12
